{
  "main": {
    "id": "120b9b0797bcfc7f",
    "type": "split",
    "children": [
      {
        "id": "496fdc1509609700",
        "type": "tabs",
        "children": [
          {
            "id": "c4f9f89fbbb68601",
            "type": "leaf",
            "state": {
              "type": "markdown",
              "state": {
                "file": "链上安全事件分析/landNFT.md",
                "mode": "source",
                "source": false
              }
            }
          }
        ]
      }
    ],
    "direction": "vertical"
  },
  "left": {
    "id": "34c490cc9119d44f",
    "type": "split",
    "children": [
      {
        "id": "d7dd817695585231",
        "type": "tabs",
        "children": [
          {
            "id": "69fbd48b383ab5e6",
            "type": "leaf",
            "state": {
              "type": "file-explorer",
              "state": {
                "sortOrder": "alphabetical"
              }
            }
          },
          {
            "id": "605048b8054f4470",
            "type": "leaf",
            "state": {
              "type": "search",
              "state": {
                "query": "",
                "matchingCase": false,
                "explainSearch": false,
                "collapseAll": false,
                "extraContext": false,
                "sortOrder": "alphabetical"
              }
            }
          },
          {
            "id": "061d3d9d0262d7ea",
            "type": "leaf",
            "state": {
              "type": "bookmarks",
              "state": {}
            }
          }
        ]
      }
    ],
    "direction": "horizontal",
    "width": 300
  },
  "right": {
    "id": "2a13fca54c39b037",
    "type": "split",
    "children": [
      {
        "id": "ef35f969667ac364",
        "type": "tabs",
        "children": [
          {
            "id": "7514407935ffacce",
            "type": "leaf",
            "state": {
              "type": "backlink",
              "state": {
                "file": "链上安全事件分析/landNFT.md",
                "collapseAll": false,
                "extraContext": false,
                "sortOrder": "alphabetical",
                "showSearch": false,
                "searchQuery": "",
                "backlinkCollapsed": false,
                "unlinkedCollapsed": true
              }
            }
          },
          {
            "id": "614b6e0c8acb2f99",
            "type": "leaf",
            "state": {
              "type": "outgoing-link",
              "state": {
                "file": "链上安全事件分析/landNFT.md",
                "linksCollapsed": false,
                "unlinkedCollapsed": true
              }
            }
          },
          {
            "id": "5384d6fba039263c",
            "type": "leaf",
            "state": {
              "type": "tag",
              "state": {
                "sortOrder": "frequency",
                "useHierarchy": true
              }
            }
          },
          {
            "id": "507e7394052de902",
            "type": "leaf",
            "state": {
              "type": "outline",
              "state": {
                "file": "链上安全事件分析/landNFT.md"
              }
            }
          }
        ]
      }
    ],
    "direction": "horizontal",
    "width": 300,
    "collapsed": true
  },
  "left-ribbon": {
    "hiddenItems": {
      "switcher:打开快速切换": false,
      "graph:查看关系图谱": false,
      "canvas:新建白板": false,
      "daily-notes:打开/创建今天的日记": false,
      "templates:插入模板": false,
      "command-palette:打开命令面板": false
    }
  },
  "active": "c4f9f89fbbb68601",
  "lastOpenFiles": [
    "CTF/ethernaut/csdn/Reentrance.md",
    "CTF/ethernaut/README.md",
    "CTF/ethernaut/images/Pasted image 20230516160111.png",
    "CTF/ethernaut/images/Pasted image 20230516155701.png",
    "CTF/ethernaut/images/Pasted image 20230516153630.png",
    "CTF/ethernaut/csdn/Vault.md",
    "CTF/ethernaut/ethernaut 第6-10关.md",
    "CTF/ethernaut/csdn/King.md",
    "CTF/ethernaut/images/Pasted image 20230516135738.png",
    "CTF/ethernaut/images/Pasted image 20230516152409.png",
    "CTF/ethernaut/images/Pasted image 20230516152204.png",
    "CTF/ethernaut/images/Pasted image 20230516141044.png",
    "链上安全事件分析/README.md",
    "CTF/ethernaut/images/Pasted image 20230516140338.png",
    "CTF/ethernaut/images/Pasted image 20230516135759.png",
    "链上安全事件分析/landNFT.md",
    "git/git上传代码.md",
    "链上安全事件分析/预言机攻击",
    "链上安全事件分析/回调函数攻击",
    "链上安全事件分析/合约逻辑漏洞",
    "链上安全事件分析/未检查的返回值",
    "链上安全事件分析/权限控制",
    "git/git本地和远程冲突的解决方式.md",
    "链上安全事件分析",
    "CTF/ethernaut/csdn/Delegation.md",
    "CTF/ethernaut/csdn/fallback.md",
    "CTF/ethernaut/images/Pasted image 20230515140705.png"
  ]
}